MANIFEST.in
README.rst
setup.py
django_thStorage.egg-info/PKG-INFO
django_thStorage.egg-info/SOURCES.txt
django_thStorage.egg-info/dependency_links.txt
django_thStorage.egg-info/top_level.txt
thStorage/__init__.py
thStorage/admin.py
thStorage/apps.py
thStorage/errorList.py
thStorage/models.py
thStorage/tests.py
thStorage/thStorageClient.py
thStorage/urls.py
thStorage/views.py
thStorage/migrations/0001_initial.py
thStorage/migrations/0002_auto_20200103_1718.py
thStorage/migrations/0003_auto_20200103_1729.py
thStorage/migrations/0004_auto_20200103_1733.py
thStorage/migrations/__init__.py
thStorage/static/css/chunk-vendors.0340a989.css
thStorage/static/css/chunk-vendors.b80cec6e.css
thStorage/static/css/home.23ba756e.css
thStorage/static/css/home.59775ea4.css
thStorage/static/css/home.5d88cebc.css
thStorage/static/css/home.81430b1d.css
thStorage/static/css/home.8a528f50.css
thStorage/static/css/home.9cd510b0.css
thStorage/static/css/home.a009f294.css
thStorage/static/css/home.a88f2ff6.css
thStorage/static/css/home.acb2cd57.css
thStorage/static/css/home.ebfa9195.css
thStorage/static/css/home.fa3ae4e6.css
thStorage/static/css/recycle.f5b4cb3b.css
thStorage/static/fonts/element-icons.535877f5.woff
thStorage/static/fonts/element-icons.732389de.ttf
thStorage/static/img/default_icon_b.4d8feee1.png
thStorage/static/img/favicon.ico
thStorage/static/img/folder_icon_b.d6e72493.png
thStorage/static/js/chunk-vendors.34795518.js
thStorage/static/js/chunk-vendors.d728f416.js
thStorage/static/js/chunk-vendors.e5abc264.js
thStorage/static/js/home.0c53fc2c.js
thStorage/static/js/home.30aacc65.js
thStorage/static/js/home.411d9a71.js
thStorage/static/js/home.45647ead.js
thStorage/static/js/home.749b86ca.js
thStorage/static/js/home.97c5f275.js
thStorage/static/js/home.ab3dfc41.js
thStorage/static/js/home.bf2f6cf0.js
thStorage/static/js/home.c3912e20.js
thStorage/static/js/home.d3e6b28a.js
thStorage/static/js/home.e357dda8.js
thStorage/static/js/home.f3a3f78c.js
thStorage/static/js/recycle.02bad639.js
thStorage/static/js/recycle.ad38a770.js
thStorage/static/js/recycle.f84ca1f7.js
thStorage/templates/home_old.html
