Metadata-Version: 2.1
Name: django-thStorage
Version: 1.1.2
Summary: A simple django app to use thuri web visual apps
Home-page: https://www.nscc-tj.cn
Author: Lichangsong&Tianyang
Author-email: lics@nscc-tj.cn
License: BSD License
Platform: UNKNOWN
Classifier: Framework :: Django
Classifier: Framework :: Django :: 2.0
Classifier: Intended Audience :: Developers
Classifier: License :: OSI Approved :: BSD License
Classifier: Operating System :: OS Independent
Classifier: Programming Language :: Python
Classifier: Programming Language :: Python :: 3
Classifier: Programming Language :: Python :: 3.6
Classifier: Programming Language :: Python :: 3.7
Classifier: Topic :: Internet :: WWW/HTTP
Classifier: Topic :: Internet :: WWW/HTTP :: Dynamic Content
